query_exporter/__init__.py
query_exporter/carto.py
query_exporter/config.py
query_exporter/conftest.py
query_exporter/db.py
query_exporter/loop.py
query_exporter/main.py
query_exporter/tests/__init__.py
query_exporter/tests/fakes.py
query_exporter/tests/test_config.py
query_exporter/tests/test_db.py
query_exporter/tests/test_loop.py
query_exporter_carto-1.5.1.dist-info/LICENSE.txt
query_exporter_carto-1.5.1.dist-info/METADATA
query_exporter_carto-1.5.1.dist-info/WHEEL
query_exporter_carto-1.5.1.dist-info/entry_points.txt
query_exporter_carto-1.5.1.dist-info/top_level.txt
query_exporter_carto-1.5.1.dist-info/RECORD
