Metadata-Version: 2.1
Name: query-exporter-carto
Version: 1.5.1
Summary: Publish Prometheus metrics generated from SQL queries (also for CARTO SQL API).
Home-page: https://github.com/GeographicaGS/query-exporter
Author: Geographica.gs (fork from https://github.com/albertodonato/query-exporter)
Author-email: 
Maintainer: Daniel Ramirez
Maintainer-email: daniel.ramirez@geographica.com
License: GPLv3+
Keywords: sql metric prometheus exporter
Platform: UNKNOWN
Classifier: Development Status :: 4 - Beta
Classifier: Intended Audience :: System Administrators
Classifier: License :: OSI Approved :: GNU General Public License (GPL)
Classifier: Operating System :: POSIX :: Linux
Classifier: Programming Language :: Python :: 3.6
Classifier: Programming Language :: Python :: 3.7
Classifier: Topic :: Utilities
Requires-Dist: aiohttp
Requires-Dist: prometheus-client
Requires-Dist: prometheus-aioexporter (>=1.5.1)
Requires-Dist: PyYaml
Requires-Dist: SQLAlchemy (==1.3.0b2)
Requires-Dist: sqlalchemy-aio
Requires-Dist: toolrack (>=2.1.0)
Requires-Dist: geographica-longitude (==1.0.0a1)
Provides-Extra: testing
Requires-Dist: pytest ; extra == 'testing'
Requires-Dist: pytest-asyncio ; extra == 'testing'
Requires-Dist: pytest-mock ; extra == 'testing'
